cwriter/__init__.py
cwriter/cwriter.py
cwriter-0.1.0a4.dist-info/LICENSE.txt
cwriter-0.1.0a4.dist-info/METADATA
cwriter-0.1.0a4.dist-info/WHEEL
cwriter-0.1.0a4.dist-info/top_level.txt
cwriter-0.1.0a4.dist-info/RECORD
