Metadata-Version: 2.1
Name: cwriter
Version: 0.1.0a4
Summary: C/C++ file generator
Home-page: https://gitlab.com/felingineer/cwriter
Download-URL: https://gitlab.com/felingineer/cwriter
Author: Guillermo Romero (Gato)
Author-email: gato@felingineering.com
License: BSD-2-Clause
Keywords: C,C++,GENERATE
Classifier: Development Status :: 3 - Alpha
Classifier: Intended Audience :: Developers
Classifier: Topic :: Utilities
Classifier: Topic :: Software Development :: Code Generators
Classifier: Programming Language :: C
Classifier: Programming Language :: C++
Classifier: License :: OSI Approved :: BSD License
Classifier: Programming Language :: Python :: 3
Classifier: Operating System :: OS Independent
License-File: LICENSE.txt
